{
  "A8ABBA": {
    "type": "date"
  },
  "BC5B57": {
    "type": "radio",
    "options": ["vor Eingriff", "nach Eingriff", "zwischen Eingriff", "Monitoring"]
  },
  "BF3639": {
    "type": "date"
  },
  "C7C3B7": {
    "type": "date"
  },
  "CF3C22": {
    "type": "date"
  },
  "DA2D73": {
    "type": "date"
  },
  "DA9CGG": {
    "type": "date"
  },
  "F285B2": {
    "type": "date"
  },
  "F5G576": {
    "type": "date"
  },
  "G73958": {
    "type": "date"
  },
  "G79CA9": {
    "type": "checkbox",
    "true-value": "Ja",
    "false-value": "Nein"
  },
  "G7F25F": {
    "type": "checkbox",
    "true-value": "Ja",
    "false-value": "Nein"
  },
  "G814D2": {
    "type": "checkbox",
    "true-value": "Ja",
    "false-value": "Nein"
  },
  "GB6DF3": {
    "type": "checkbox",
    "true-value": "Ja",
    "false-value": "Nein"
  },
  "GF856C": {
    "type": "date"
  },
  "K343FVC": {
    "type": "date"
  },
  "QD45G7": {
    "type": "date"
  }
}